{"default":{"Panel1":{"Id":"Panel1",
"Title":"Search 1",
"Position":{"Left":"220px",
"Top":"30px",
"Width":"525px",
"Height":"600px"},
"Panels":[],
"ZIndex":1}},
"yesyes":{"Panel1":{"Id":"Panel1",
"Title":"Search 1",
"Position":{"Left":"564px",
"Top":"52px",
"Width":"535px",
"Height":"371px"},
"Panels":[],
"Url":"http://corpus3.aac.ac.at/switch?operation=searchRetrieve&query=haus&x-context=clarin.at:icltt:ddc:barock&x-format=html&version=1.2",
"ZIndex":1}},
"nono":{"Panel1":{"Id":"Panel1",
"Title":"Search 1",
"Position":{"Left":"350px",
"Top":"279px",
"Width":"535px",
"Height":"371px"},
"Panels":[],
"Url":"http://corpus3.aac.ac.at/switch?operation=searchRetrieve&query=wasser&x-context=clarin.at:icltt:ddc:barock&x-format=html&version=1.2",
"ZIndex":1}}}